uncovr/__init__.py
uncovr/buildModelData.py
uncovr/helperFunctions.py
uncovr/indepAndDep.py
uncovr/uncovrApi.py
uncovr-0.1.0.dist-info/LICENSE
uncovr-0.1.0.dist-info/METADATA
uncovr-0.1.0.dist-info/WHEEL
uncovr-0.1.0.dist-info/top_level.txt
uncovr-0.1.0.dist-info/RECORD
